pyjags/__init__.py
pyjags/_version.py
pyjags/adaptive_sampling.py
pyjags/arviz.py
pyjags/chain_utilities.py
pyjags/console.cpython-37m-darwin.so
pyjags/dic.py
pyjags/io.py
pyjags/model.py
pyjags/modules.py
pyjags/progressbar.py
pyjags-1.3.1.dist-info/LICENSE
pyjags-1.3.1.dist-info/METADATA
pyjags-1.3.1.dist-info/WHEEL
pyjags-1.3.1.dist-info/top_level.txt
pyjags-1.3.1.dist-info/RECORD
