Metadata-Version: 2.1
Name: pyjags
Version: 1.3.1
Summary: Python interface to JAGS library for Bayesian data analysis.
Home-page: https://github.com/michaelnowotny/pyjags
Author: Tomasz Miąsko, Michael Nowotny
Author-email: tomasz.miasko@gmail.com, nowotnym@gmail.com
License: GPLv2
Platform: UNKNOWN
Classifier: Development Status :: 4 - Beta
Classifier: License :: OSI Approved :: GNU General Public License v2 (GPLv2)
Classifier: Operating System :: POSIX
Classifier: Programming Language :: C++
Classifier: Programming Language :: Python :: 2
Classifier: Programming Language :: Python :: 2.7
Classifier: Programming Language :: Python :: 3
Classifier: Programming Language :: Python :: 3.4
Classifier: Programming Language :: Python :: 3.5
Classifier: Programming Language :: Python :: 3.6
Classifier: Programming Language :: Python :: 3.7
Classifier: Programming Language :: Python :: 3.8
Classifier: Programming Language :: Python
Classifier: Topic :: Scientific/Engineering :: Information Analysis
Classifier: Topic :: Scientific/Engineering
Requires-Dist: arviz
Requires-Dist: deepdish
Requires-Dist: numpy
